SuperGemini/VERSION
SuperGemini/__init__.py
SuperGemini/__main__.py
SuperGemini/version.py
SuperGemini/Agents/__init__.py
SuperGemini/Agents/backend-architect.md
SuperGemini/Agents/devops-architect.md
SuperGemini/Agents/frontend-architect.md
SuperGemini/Agents/learning-guide.md
SuperGemini/Agents/performance-engineer.md
SuperGemini/Agents/python-expert.md
SuperGemini/Agents/quality-engineer.md
SuperGemini/Agents/refactoring-expert.md
SuperGemini/Agents/requirements-analyst.md
SuperGemini/Agents/root-cause-analyst.md
SuperGemini/Agents/security-engineer.md
SuperGemini/Agents/system-architect.md
SuperGemini/Agents/technical-writer.md
SuperGemini/Commands/__init__.py
SuperGemini/Commands/analyze.toml
SuperGemini/Commands/brainstorm.toml
SuperGemini/Commands/build.toml
SuperGemini/Commands/business-panel.toml
SuperGemini/Commands/cleanup.toml
SuperGemini/Commands/design.toml
SuperGemini/Commands/document.toml
SuperGemini/Commands/estimate.toml
SuperGemini/Commands/explain.toml
SuperGemini/Commands/git.toml
SuperGemini/Commands/implement.toml
SuperGemini/Commands/improve.toml
SuperGemini/Commands/index.toml
SuperGemini/Commands/load.toml
SuperGemini/Commands/reflect.toml
SuperGemini/Commands/research.toml
SuperGemini/Commands/save.toml
SuperGemini/Commands/select-tool.toml
SuperGemini/Commands/spawn.toml
SuperGemini/Commands/spec-panel.toml
SuperGemini/Commands/task.toml
SuperGemini/Commands/test.toml
SuperGemini/Commands/troubleshoot.toml
SuperGemini/Commands/workflow.toml
SuperGemini/Config/__init__.py
SuperGemini/Core/BUSINESS_PANEL_EXAMPLES.md
SuperGemini/Core/BUSINESS_SYMBOLS.md
SuperGemini/Core/FLAGS.md
SuperGemini/Core/PRINCIPLES.md
SuperGemini/Core/RESEARCH_CONFIG.md
SuperGemini/Core/RULES.md
SuperGemini/Core/__init__.py
SuperGemini/MCP/MCP_Context7.md
SuperGemini/MCP/MCP_Magic.md
SuperGemini/MCP/MCP_Morphllm.md
SuperGemini/MCP/MCP_Playwright.md
SuperGemini/MCP/MCP_Sequential.md
SuperGemini/MCP/MCP_Serena.md
SuperGemini/MCP/__init__.py
supergemini-4.3.0.dist-info/licenses/LICENSE
supergemini-4.3.0.dist-info/METADATA
supergemini-4.3.0.dist-info/WHEEL
supergemini-4.3.0.dist-info/entry_points.txt
supergemini-4.3.0.dist-info/top_level.txt
supergemini-4.3.0.dist-info/RECORD
