Metadata-Version: 2.4
Name: SuperGemini
Version: 4.3.0
Summary: SuperGemini Framework Management Hub - AI-enhanced development framework for Gemini single-agent architecture
Home-page: https://github.com/SuperClaude-Org/SuperGemini_Framework
Author: hyunjae lim, NomenAK, Mithun Gowda B
Author-email: hyunjae lim <thecurrent.lim@gmail.com>, NomenAK <anton.knoery@gmail.com>, Mithun Gowda B <mithungowda.b7411@gmail.com>
License: MIT
Project-URL: Homepage, https://github.com/SuperClaude-Org/SuperGemini_Framework
Project-URL: GitHub, https://github.com/SuperClaude-Org/SuperGemini_Framework
Project-URL: Bug Tracker, https://github.com/SuperClaude-Org/SuperGemini_Framework/issues
Keywords: gemini,ai,automation,framework,mcp,agents,development,code-generation,assistant
Classifier: Development Status :: 4 - Beta
Classifier: Intended Audience :: Developers
Classifier: License :: OSI Approved :: MIT License
Classifier: Operating System :: OS Independent
Classifier: Programming Language :: Python :: 3
Classifier: Programming Language :: Python :: 3.8
Classifier: Programming Language :: Python :: 3.9
Classifier: Programming Language :: Python :: 3.10
Classifier: Programming Language :: Python :: 3.11
Classifier: Programming Language :: Python :: 3.12
Classifier: Topic :: Software Development :: Libraries :: Python Modules
Classifier: Topic :: Software Development :: Code Generators
Classifier: Topic :: Scientific/Engineering :: Artificial Intelligence
Classifier: Environment :: Console
Requires-Python: >=3.8
License-File: LICENSE
Requires-Dist: setuptools>=45.0.0
Requires-Dist: importlib-metadata>=1.0.0; python_version < "3.8"
Provides-Extra: dev
Requires-Dist: pytest>=6.0; extra == "dev"
Requires-Dist: pytest-cov>=2.0; extra == "dev"
Requires-Dist: black>=22.0; extra == "dev"
Requires-Dist: flake8>=4.0; extra == "dev"
Requires-Dist: mypy>=0.900; extra == "dev"
Provides-Extra: test
Requires-Dist: pytest>=6.0; extra == "test"
Requires-Dist: pytest-cov>=2.0; extra == "test"
Dynamic: author
Dynamic: home-page
Dynamic: license-file
Dynamic: requires-python
